zamzar/__init__.py
zamzar/zamzar.py
pyzamzar-1.0.4.dist-info/METADATA
pyzamzar-1.0.4.dist-info/WHEEL
pyzamzar-1.0.4.dist-info/top_level.txt
pyzamzar-1.0.4.dist-info/RECORD
