Metadata-Version: 2.1
Name: pyzamzar
Version: 1.0.4
Summary: Python SDK for the Zamzar file conversion API
Author: Nemuel Wainaina
